code_to_text/__init__.py
code_to_text/main.py
tests/__init__.py
tests/test_main.py
code_to_text-0.2.dist-info/METADATA
code_to_text-0.2.dist-info/WHEEL
code_to_text-0.2.dist-info/entry_points.txt
code_to_text-0.2.dist-info/top_level.txt
code_to_text-0.2.dist-info/RECORD
